rratelimit-0.0.4.dist-info/RECORD
rratelimit-0.0.4.dist-info/DESCRIPTION.rst
rratelimit-0.0.4.dist-info/WHEEL
rratelimit-0.0.4.dist-info/METADATA
rratelimit-0.0.4.dist-info/metadata.json
rratelimit-0.0.4.dist-info/top_level.txt
rratelimit/utils.py
rratelimit/limiters.py
rratelimit/exceptions.py
rratelimit/__init__.py
rratelimit/lua/list_checked_insert.lua
rratelimit/lua/list_check.lua
rratelimit/lua/list_insert.lua
rratelimit/lua/simple_checked_insert.lua
rratelimit/lua/hash_insert.lua
rratelimit/lua/simple_insert.lua
rratelimit/lua/simple_check.lua
rratelimit/lua/hash_checked_insert.lua
rratelimit/lua/hash_check.lua
