Metadata-Version: 2.0
Name: rratelimit
Version: 0.0.4
Summary: Rate limiting classes for redis and redis-py
Home-page: http://github.com/HeyImAlex/rratelimit
Author: Alex Guerra
Author-email: alex@heyimalex.com
License: MIT
Platform: UNKNOWN
Classifier: Development Status :: 4 - Beta
Classifier: License :: OSI Approved :: MIT License
Classifier: Intended Audience :: Developers
Classifier: Programming Language :: Python :: 2.7
Classifier: Programming Language :: Python :: 3
Provides-Extra: test
Requires-Dist: nose (>=1.0); extra == 'test'
Requires-Dist: redis; extra == 'test'
